package net.basket.db;

import java.sql.Connection;
import javax.naming.Context;
import javax.naming.InitialContext;
import javax.sql.DataSource;

public class BasketDAO
{
  private Connection getConnection()
    throws Exception
  {
    Connection con = null;
    Context init = new InitialContext();
    
    DataSource ds = (DataSource)init.lookup("java:comp/env/jdbc/smtrax3");
    
    con = ds.getConnection();
    return con;
  }
  
  /* Error */
  public void basketAdd(BasketBean basketbean)
  {
    // Byte code:
    //   0: aconst_null
    //   1: astore_2
    //   2: aconst_null
    //   3: astore_3
    //   4: aconst_null
    //   5: astore 4
    //   7: ldc 42
    //   9: astore 5
    //   11: iconst_0
    //   12: istore 6
    //   14: aload_0
    //   15: invokespecial 44	net/basket/db/BasketDAO:getConnection	()Ljava/sql/Connection;
    //   18: astore_2
    //   19: ldc 45
    //   21: astore 5
    //   23: aload_2
    //   24: aload 5
    //   26: invokeinterface 47 2 0
    //   31: astore_3
    //   32: aload_3
    //   33: invokeinterface 53 1 0
    //   38: astore 4
    //   40: aload 4
    //   42: invokeinterface 59 1 0
    //   47: ifeq +18 -> 65
    //   50: aload 4
    //   52: iconst_1
    //   53: invokeinterface 65 2 0
    //   58: iconst_1
    //   59: iadd
    //   60: istore 6
    //   62: goto +6 -> 68
    //   65: iconst_1
    //   66: istore 6
    //   68: ldc 69
    //   70: astore 5
    //   72: aload_2
    //   73: aload 5
    //   75: invokeinterface 47 2 0
    //   80: astore_3
    //   81: aload_3
    //   82: iconst_1
    //   83: iload 6
    //   85: invokeinterface 71 3 0
    //   90: aload_3
    //   91: iconst_2
    //   92: aload_1
    //   93: invokevirtual 75	net/basket/db/BasketBean:getB_m_id	()Ljava/lang/String;
    //   96: invokeinterface 81 3 0
    //   101: aload_3
    //   102: iconst_3
    //   103: aload_1
    //   104: invokevirtual 85	net/basket/db/BasketBean:getB_g_num	()I
    //   107: invokeinterface 71 3 0
    //   112: aload_3
    //   113: iconst_4
    //   114: aload_1
    //   115: invokevirtual 89	net/basket/db/BasketBean:getB_g_amount	()I
    //   118: invokeinterface 71 3 0
    //   123: aload_3
    //   124: iconst_5
    //   125: aload_1
    //   126: invokevirtual 92	net/basket/db/BasketBean:getB_g_size	()Ljava/lang/String;
    //   129: invokeinterface 81 3 0
    //   134: aload_3
    //   135: bipush 6
    //   137: aload_1
    //   138: invokevirtual 95	net/basket/db/BasketBean:getB_g_color	()Ljava/lang/String;
    //   141: invokeinterface 81 3 0
    //   146: aload_3
    //   147: invokeinterface 98 1 0
    //   152: pop
    //   153: goto +112 -> 265
    //   156: astore 7
    //   158: aload 7
    //   160: invokevirtual 101	java/lang/Exception:printStackTrace	()V
    //   163: aload 4
    //   165: ifnull +15 -> 180
    //   168: aload 4
    //   170: invokeinterface 104 1 0
    //   175: goto +5 -> 180
    //   178: astore 9
    //   180: aload_3
    //   181: ifnull +14 -> 195
    //   184: aload_3
    //   185: invokeinterface 107 1 0
    //   190: goto +5 -> 195
    //   193: astore 9
    //   195: aload_2
    //   196: ifnull +116 -> 312
    //   199: aload_2
    //   200: invokeinterface 108 1 0
    //   205: goto +107 -> 312
    //   208: astore 9
    //   210: goto +102 -> 312
    //   213: astore 8
    //   215: aload 4
    //   217: ifnull +15 -> 232
    //   220: aload 4
    //   222: invokeinterface 104 1 0
    //   227: goto +5 -> 232
    //   230: astore 9
    //   232: aload_3
    //   233: ifnull +14 -> 247
    //   236: aload_3
    //   237: invokeinterface 107 1 0
    //   242: goto +5 -> 247
    //   245: astore 9
    //   247: aload_2
    //   248: ifnull +14 -> 262
    //   251: aload_2
    //   252: invokeinterface 108 1 0
    //   257: goto +5 -> 262
    //   260: astore 9
    //   262: aload 8
    //   264: athrow
    //   265: aload 4
    //   267: ifnull +15 -> 282
    //   270: aload 4
    //   272: invokeinterface 104 1 0
    //   277: goto +5 -> 282
    //   280: astore 9
    //   282: aload_3
    //   283: ifnull +14 -> 297
    //   286: aload_3
    //   287: invokeinterface 107 1 0
    //   292: goto +5 -> 297
    //   295: astore 9
    //   297: aload_2
    //   298: ifnull +14 -> 312
    //   301: aload_2
    //   302: invokeinterface 108 1 0
    //   307: goto +5 -> 312
    //   310: astore 9
    //   312: return
    // Line number table:
    //   Java source line #33	-> byte code offset #0
    //   Java source line #34	-> byte code offset #2
    //   Java source line #35	-> byte code offset #4
    //   Java source line #36	-> byte code offset #7
    //   Java source line #37	-> byte code offset #11
    //   Java source line #40	-> byte code offset #14
    //   Java source line #42	-> byte code offset #19
    //   Java source line #43	-> byte code offset #23
    //   Java source line #44	-> byte code offset #32
    //   Java source line #45	-> byte code offset #40
    //   Java source line #46	-> byte code offset #50
    //   Java source line #47	-> byte code offset #62
    //   Java source line #48	-> byte code offset #65
    //   Java source line #51	-> byte code offset #68
    //   Java source line #52	-> byte code offset #72
    //   Java source line #53	-> byte code offset #81
    //   Java source line #54	-> byte code offset #90
    //   Java source line #55	-> byte code offset #101
    //   Java source line #56	-> byte code offset #112
    //   Java source line #57	-> byte code offset #123
    //   Java source line #58	-> byte code offset #134
    //   Java source line #60	-> byte code offset #146
    //   Java source line #61	-> byte code offset #153
    //   Java source line #62	-> byte code offset #158
    //   Java source line #64	-> byte code offset #163
    //   Java source line #65	-> byte code offset #180
    //   Java source line #66	-> byte code offset #195
    //   Java source line #63	-> byte code offset #213
    //   Java source line #64	-> byte code offset #215
    //   Java source line #65	-> byte code offset #232
    //   Java source line #66	-> byte code offset #247
    //   Java source line #67	-> byte code offset #262
    //   Java source line #64	-> byte code offset #265
    //   Java source line #65	-> byte code offset #282
    //   Java source line #66	-> byte code offset #297
    //   Java source line #68	-> byte code offset #312
    // Local variable table:
    //   start	length	slot	name	signature
    //   0	313	0	this	BasketDAO
    //   0	313	1	basketbean	BasketBean
    //   1	301	2	con	Connection
    //   3	284	3	pstmt	java.sql.PreparedStatement
    //   5	266	4	rs	java.sql.ResultSet
    //   9	65	5	sql	String
    //   12	72	6	b_num	int
    //   156	3	7	e	Exception
    //   213	50	8	localObject	Object
    //   178	1	9	localSQLException	java.sql.SQLException
    //   193	1	9	localSQLException1	java.sql.SQLException
    //   208	1	9	localSQLException2	java.sql.SQLException
    //   230	1	9	localSQLException3	java.sql.SQLException
    //   245	1	9	localSQLException4	java.sql.SQLException
    //   260	1	9	localSQLException5	java.sql.SQLException
    //   280	1	9	localSQLException6	java.sql.SQLException
    //   295	1	9	localSQLException7	java.sql.SQLException
    //   310	1	9	localSQLException8	java.sql.SQLException
    // Exception table:
    //   from	to	target	type
    //   14	153	156	java/lang/Exception
    //   168	175	178	java/sql/SQLException
    //   184	190	193	java/sql/SQLException
    //   199	205	208	java/sql/SQLException
    //   14	163	213	finally
    //   220	227	230	java/sql/SQLException
    //   236	242	245	java/sql/SQLException
    //   251	257	260	java/sql/SQLException
    //   270	277	280	java/sql/SQLException
    //   286	292	295	java/sql/SQLException
    //   301	307	310	java/sql/SQLException
  }
  
  /* Error */
  public int checkGoods(BasketBean basketbean)
  {
    // Byte code:
    //   0: aconst_null
    //   1: astore_2
    //   2: aconst_null
    //   3: astore_3
    //   4: aconst_null
    //   5: astore 4
    //   7: ldc 42
    //   9: astore 5
    //   11: iconst_0
    //   12: istore 6
    //   14: aload_0
    //   15: invokespecial 44	net/basket/db/BasketDAO:getConnection	()Ljava/sql/Connection;
    //   18: astore_2
    //   19: ldc -126
    //   21: astore 5
    //   23: aload_2
    //   24: aload 5
    //   26: invokeinterface 47 2 0
    //   31: astore_3
    //   32: aload_3
    //   33: iconst_1
    //   34: aload_1
    //   35: invokevirtual 75	net/basket/db/BasketBean:getB_m_id	()Ljava/lang/String;
    //   38: invokeinterface 81 3 0
    //   43: aload_3
    //   44: iconst_2
    //   45: aload_1
    //   46: invokevirtual 85	net/basket/db/BasketBean:getB_g_num	()I
    //   49: invokeinterface 71 3 0
    //   54: aload_3
    //   55: iconst_3
    //   56: aload_1
    //   57: invokevirtual 92	net/basket/db/BasketBean:getB_g_size	()Ljava/lang/String;
    //   60: invokeinterface 81 3 0
    //   65: aload_3
    //   66: iconst_4
    //   67: aload_1
    //   68: invokevirtual 95	net/basket/db/BasketBean:getB_g_color	()Ljava/lang/String;
    //   71: invokeinterface 81 3 0
    //   76: aload_3
    //   77: invokeinterface 53 1 0
    //   82: astore 4
    //   84: aload 4
    //   86: invokeinterface 59 1 0
    //   91: ifeq +193 -> 284
    //   94: iconst_1
    //   95: istore 6
    //   97: ldc -124
    //   99: astore 5
    //   101: aload_2
    //   102: aload 5
    //   104: invokeinterface 47 2 0
    //   109: astore_3
    //   110: aload_3
    //   111: iconst_1
    //   112: aload_1
    //   113: invokevirtual 89	net/basket/db/BasketBean:getB_g_amount	()I
    //   116: invokeinterface 71 3 0
    //   121: aload_3
    //   122: iconst_2
    //   123: aload_1
    //   124: invokevirtual 75	net/basket/db/BasketBean:getB_m_id	()Ljava/lang/String;
    //   127: invokeinterface 81 3 0
    //   132: aload_3
    //   133: iconst_3
    //   134: aload_1
    //   135: invokevirtual 85	net/basket/db/BasketBean:getB_g_num	()I
    //   138: invokeinterface 71 3 0
    //   143: aload_3
    //   144: iconst_4
    //   145: aload_1
    //   146: invokevirtual 92	net/basket/db/BasketBean:getB_g_size	()Ljava/lang/String;
    //   149: invokeinterface 81 3 0
    //   154: aload_3
    //   155: iconst_5
    //   156: aload_1
    //   157: invokevirtual 95	net/basket/db/BasketBean:getB_g_color	()Ljava/lang/String;
    //   160: invokeinterface 81 3 0
    //   165: aload_3
    //   166: invokeinterface 98 1 0
    //   171: pop
    //   172: goto +112 -> 284
    //   175: astore 7
    //   177: aload 7
    //   179: invokevirtual 101	java/lang/Exception:printStackTrace	()V
    //   182: aload 4
    //   184: ifnull +15 -> 199
    //   187: aload 4
    //   189: invokeinterface 104 1 0
    //   194: goto +5 -> 199
    //   197: astore 9
    //   199: aload_3
    //   200: ifnull +14 -> 214
    //   203: aload_3
    //   204: invokeinterface 107 1 0
    //   209: goto +5 -> 214
    //   212: astore 9
    //   214: aload_2
    //   215: ifnull +116 -> 331
    //   218: aload_2
    //   219: invokeinterface 108 1 0
    //   224: goto +107 -> 331
    //   227: astore 9
    //   229: goto +102 -> 331
    //   232: astore 8
    //   234: aload 4
    //   236: ifnull +15 -> 251
    //   239: aload 4
    //   241: invokeinterface 104 1 0
    //   246: goto +5 -> 251
    //   249: astore 9
    //   251: aload_3
    //   252: ifnull +14 -> 266
    //   255: aload_3
    //   256: invokeinterface 107 1 0
    //   261: goto +5 -> 266
    //   264: astore 9
    //   266: aload_2
    //   267: ifnull +14 -> 281
    //   270: aload_2
    //   271: invokeinterface 108 1 0
    //   276: goto +5 -> 281
    //   279: astore 9
    //   281: aload 8
    //   283: athrow
    //   284: aload 4
    //   286: ifnull +15 -> 301
    //   289: aload 4
    //   291: invokeinterface 104 1 0
    //   296: goto +5 -> 301
    //   299: astore 9
    //   301: aload_3
    //   302: ifnull +14 -> 316
    //   305: aload_3
    //   306: invokeinterface 107 1 0
    //   311: goto +5 -> 316
    //   314: astore 9
    //   316: aload_2
    //   317: ifnull +14 -> 331
    //   320: aload_2
    //   321: invokeinterface 108 1 0
    //   326: goto +5 -> 331
    //   329: astore 9
    //   331: iload 6
    //   333: ireturn
    // Line number table:
    //   Java source line #72	-> byte code offset #0
    //   Java source line #73	-> byte code offset #2
    //   Java source line #74	-> byte code offset #4
    //   Java source line #75	-> byte code offset #7
    //   Java source line #76	-> byte code offset #11
    //   Java source line #79	-> byte code offset #14
    //   Java source line #82	-> byte code offset #19
    //   Java source line #83	-> byte code offset #23
    //   Java source line #84	-> byte code offset #32
    //   Java source line #85	-> byte code offset #43
    //   Java source line #86	-> byte code offset #54
    //   Java source line #87	-> byte code offset #65
    //   Java source line #89	-> byte code offset #76
    //   Java source line #95	-> byte code offset #84
    //   Java source line #96	-> byte code offset #94
    //   Java source line #97	-> byte code offset #97
    //   Java source line #98	-> byte code offset #101
    //   Java source line #99	-> byte code offset #110
    //   Java source line #100	-> byte code offset #121
    //   Java source line #101	-> byte code offset #132
    //   Java source line #102	-> byte code offset #143
    //   Java source line #103	-> byte code offset #154
    //   Java source line #104	-> byte code offset #165
    //   Java source line #106	-> byte code offset #172
    //   Java source line #107	-> byte code offset #177
    //   Java source line #109	-> byte code offset #182
    //   Java source line #110	-> byte code offset #199
    //   Java source line #111	-> byte code offset #214
    //   Java source line #108	-> byte code offset #232
    //   Java source line #109	-> byte code offset #234
    //   Java source line #110	-> byte code offset #251
    //   Java source line #111	-> byte code offset #266
    //   Java source line #112	-> byte code offset #281
    //   Java source line #109	-> byte code offset #284
    //   Java source line #110	-> byte code offset #301
    //   Java source line #111	-> byte code offset #316
    //   Java source line #114	-> byte code offset #331
    // Local variable table:
    //   start	length	slot	name	signature
    //   0	334	0	this	BasketDAO
    //   0	334	1	basketbean	BasketBean
    //   1	320	2	con	Connection
    //   3	303	3	pstmt	java.sql.PreparedStatement
    //   5	285	4	rs	java.sql.ResultSet
    //   9	94	5	sql	String
    //   12	320	6	check	int
    //   175	3	7	e	Exception
    //   232	50	8	localObject	Object
    //   197	1	9	localSQLException	java.sql.SQLException
    //   212	1	9	localSQLException1	java.sql.SQLException
    //   227	1	9	localSQLException2	java.sql.SQLException
    //   249	1	9	localSQLException3	java.sql.SQLException
    //   264	1	9	localSQLException4	java.sql.SQLException
    //   279	1	9	localSQLException5	java.sql.SQLException
    //   299	1	9	localSQLException6	java.sql.SQLException
    //   314	1	9	localSQLException7	java.sql.SQLException
    //   329	1	9	localSQLException8	java.sql.SQLException
    // Exception table:
    //   from	to	target	type
    //   14	172	175	java/lang/Exception
    //   187	194	197	java/sql/SQLException
    //   203	209	212	java/sql/SQLException
    //   218	224	227	java/sql/SQLException
    //   14	182	232	finally
    //   239	246	249	java/sql/SQLException
    //   255	261	264	java/sql/SQLException
    //   270	276	279	java/sql/SQLException
    //   289	296	299	java/sql/SQLException
    //   305	311	314	java/sql/SQLException
    //   320	326	329	java/sql/SQLException
  }
  
  /* Error */
  public java.util.Vector getBasketList(String id)
  {
    // Byte code:
    //   0: aconst_null
    //   1: astore_2
    //   2: aconst_null
    //   3: astore_3
    //   4: aconst_null
    //   5: astore 4
    //   7: aconst_null
    //   8: astore 5
    //   10: aconst_null
    //   11: astore 6
    //   13: ldc 42
    //   15: astore 7
    //   17: new 137	java/util/Vector
    //   20: dup
    //   21: invokespecial 139	java/util/Vector:<init>	()V
    //   24: astore 8
    //   26: new 140	java/util/ArrayList
    //   29: dup
    //   30: invokespecial 142	java/util/ArrayList:<init>	()V
    //   33: astore 9
    //   35: new 140	java/util/ArrayList
    //   38: dup
    //   39: invokespecial 142	java/util/ArrayList:<init>	()V
    //   42: astore 10
    //   44: aload_0
    //   45: invokespecial 44	net/basket/db/BasketDAO:getConnection	()Ljava/sql/Connection;
    //   48: astore_2
    //   49: ldc -113
    //   51: astore 7
    //   53: aload_2
    //   54: aload 7
    //   56: invokeinterface 47 2 0
    //   61: astore_3
    //   62: aload_3
    //   63: iconst_1
    //   64: aload_1
    //   65: invokeinterface 81 3 0
    //   70: aload_3
    //   71: invokeinterface 53 1 0
    //   76: astore 4
    //   78: goto +227 -> 305
    //   81: new 76	net/basket/db/BasketBean
    //   84: dup
    //   85: invokespecial 145	net/basket/db/BasketBean:<init>	()V
    //   88: astore 11
    //   90: aload 11
    //   92: aload 4
    //   94: ldc -110
    //   96: invokeinterface 148 2 0
    //   101: invokevirtual 152	net/basket/db/BasketBean:setB_date	(Ljava/util/Date;)V
    //   104: aload 11
    //   106: aload 4
    //   108: ldc -100
    //   110: invokeinterface 158 2 0
    //   115: invokevirtual 161	net/basket/db/BasketBean:setB_g_amount	(I)V
    //   118: aload 11
    //   120: aload 4
    //   122: ldc -91
    //   124: invokeinterface 167 2 0
    //   129: invokevirtual 171	net/basket/db/BasketBean:setB_g_color	(Ljava/lang/String;)V
    //   132: aload 11
    //   134: aload 4
    //   136: ldc -81
    //   138: invokeinterface 158 2 0
    //   143: invokevirtual 177	net/basket/db/BasketBean:setB_g_num	(I)V
    //   146: aload 11
    //   148: aload 4
    //   150: ldc -76
    //   152: invokeinterface 167 2 0
    //   157: invokevirtual 182	net/basket/db/BasketBean:setB_g_size	(Ljava/lang/String;)V
    //   160: aload 11
    //   162: aload 4
    //   164: ldc -71
    //   166: invokeinterface 167 2 0
    //   171: invokevirtual 187	net/basket/db/BasketBean:setB_m_id	(Ljava/lang/String;)V
    //   174: aload 11
    //   176: aload 4
    //   178: ldc -66
    //   180: invokeinterface 158 2 0
    //   185: invokevirtual 191	net/basket/db/BasketBean:setB_num	(I)V
    //   188: aload 9
    //   190: aload 11
    //   192: invokeinterface 194 2 0
    //   197: pop
    //   198: ldc -56
    //   200: astore 7
    //   202: aload_2
    //   203: aload 7
    //   205: invokeinterface 47 2 0
    //   210: astore 5
    //   212: aload 5
    //   214: iconst_1
    //   215: aload 11
    //   217: invokevirtual 85	net/basket/db/BasketBean:getB_g_num	()I
    //   220: invokeinterface 71 3 0
    //   225: aload 5
    //   227: invokeinterface 53 1 0
    //   232: astore 6
    //   234: aload 6
    //   236: invokeinterface 59 1 0
    //   241: ifeq +64 -> 305
    //   244: new 202	net/admin/goods/db/GoodsBean
    //   247: dup
    //   248: invokespecial 204	net/admin/goods/db/GoodsBean:<init>	()V
    //   251: astore 12
    //   253: aload 12
    //   255: aload 6
    //   257: ldc -51
    //   259: invokeinterface 158 2 0
    //   264: invokevirtual 207	net/admin/goods/db/GoodsBean:setPrice	(I)V
    //   267: aload 12
    //   269: aload 6
    //   271: ldc -46
    //   273: invokeinterface 167 2 0
    //   278: invokevirtual 212	net/admin/goods/db/GoodsBean:setName	(Ljava/lang/String;)V
    //   281: aload 12
    //   283: aload 6
    //   285: ldc -41
    //   287: invokeinterface 167 2 0
    //   292: invokevirtual 217	net/admin/goods/db/GoodsBean:setImage	(Ljava/lang/String;)V
    //   295: aload 10
    //   297: aload 12
    //   299: invokeinterface 194 2 0
    //   304: pop
    //   305: aload 4
    //   307: invokeinterface 59 1 0
    //   312: ifne -231 -> 81
    //   315: aload 8
    //   317: aload 9
    //   319: invokevirtual 220	java/util/Vector:add	(Ljava/lang/Object;)Z
    //   322: pop
    //   323: aload 8
    //   325: aload 10
    //   327: invokevirtual 220	java/util/Vector:add	(Ljava/lang/Object;)Z
    //   330: pop
    //   331: goto +112 -> 443
    //   334: astore 11
    //   336: aload 11
    //   338: invokevirtual 101	java/lang/Exception:printStackTrace	()V
    //   341: aload 4
    //   343: ifnull +15 -> 358
    //   346: aload 4
    //   348: invokeinterface 104 1 0
    //   353: goto +5 -> 358
    //   356: astore 14
    //   358: aload_3
    //   359: ifnull +14 -> 373
    //   362: aload_3
    //   363: invokeinterface 107 1 0
    //   368: goto +5 -> 373
    //   371: astore 14
    //   373: aload_2
    //   374: ifnull +116 -> 490
    //   377: aload_2
    //   378: invokeinterface 108 1 0
    //   383: goto +107 -> 490
    //   386: astore 14
    //   388: goto +102 -> 490
    //   391: astore 13
    //   393: aload 4
    //   395: ifnull +15 -> 410
    //   398: aload 4
    //   400: invokeinterface 104 1 0
    //   405: goto +5 -> 410
    //   408: astore 14
    //   410: aload_3
    //   411: ifnull +14 -> 425
    //   414: aload_3
    //   415: invokeinterface 107 1 0
    //   420: goto +5 -> 425
    //   423: astore 14
    //   425: aload_2
    //   426: ifnull +14 -> 440
    //   429: aload_2
    //   430: invokeinterface 108 1 0
    //   435: goto +5 -> 440
    //   438: astore 14
    //   440: aload 13
    //   442: athrow
    //   443: aload 4
    //   445: ifnull +15 -> 460
    //   448: aload 4
    //   450: invokeinterface 104 1 0
    //   455: goto +5 -> 460
    //   458: astore 14
    //   460: aload_3
    //   461: ifnull +14 -> 475
    //   464: aload_3
    //   465: invokeinterface 107 1 0
    //   470: goto +5 -> 475
    //   473: astore 14
    //   475: aload_2
    //   476: ifnull +14 -> 490
    //   479: aload_2
    //   480: invokeinterface 108 1 0
    //   485: goto +5 -> 490
    //   488: astore 14
    //   490: aload 8
    //   492: areturn
    // Line number table:
    //   Java source line #119	-> byte code offset #0
    //   Java source line #120	-> byte code offset #2
    //   Java source line #121	-> byte code offset #4
    //   Java source line #122	-> byte code offset #7
    //   Java source line #123	-> byte code offset #10
    //   Java source line #124	-> byte code offset #13
    //   Java source line #125	-> byte code offset #17
    //   Java source line #126	-> byte code offset #26
    //   Java source line #127	-> byte code offset #35
    //   Java source line #130	-> byte code offset #44
    //   Java source line #132	-> byte code offset #49
    //   Java source line #133	-> byte code offset #53
    //   Java source line #134	-> byte code offset #62
    //   Java source line #136	-> byte code offset #70
    //   Java source line #144	-> byte code offset #78
    //   Java source line #145	-> byte code offset #81
    //   Java source line #146	-> byte code offset #90
    //   Java source line #147	-> byte code offset #104
    //   Java source line #148	-> byte code offset #118
    //   Java source line #149	-> byte code offset #132
    //   Java source line #150	-> byte code offset #146
    //   Java source line #151	-> byte code offset #160
    //   Java source line #152	-> byte code offset #174
    //   Java source line #153	-> byte code offset #188
    //   Java source line #154	-> byte code offset #198
    //   Java source line #155	-> byte code offset #202
    //   Java source line #156	-> byte code offset #212
    //   Java source line #157	-> byte code offset #225
    //   Java source line #158	-> byte code offset #234
    //   Java source line #159	-> byte code offset #244
    //   Java source line #160	-> byte code offset #253
    //   Java source line #161	-> byte code offset #267
    //   Java source line #162	-> byte code offset #281
    //   Java source line #163	-> byte code offset #295
    //   Java source line #144	-> byte code offset #305
    //   Java source line #168	-> byte code offset #315
    //   Java source line #169	-> byte code offset #323
    //   Java source line #170	-> byte code offset #331
    //   Java source line #171	-> byte code offset #336
    //   Java source line #173	-> byte code offset #341
    //   Java source line #174	-> byte code offset #358
    //   Java source line #175	-> byte code offset #373
    //   Java source line #172	-> byte code offset #391
    //   Java source line #173	-> byte code offset #393
    //   Java source line #174	-> byte code offset #410
    //   Java source line #175	-> byte code offset #425
    //   Java source line #176	-> byte code offset #440
    //   Java source line #173	-> byte code offset #443
    //   Java source line #174	-> byte code offset #460
    //   Java source line #175	-> byte code offset #475
    //   Java source line #177	-> byte code offset #490
    // Local variable table:
    //   start	length	slot	name	signature
    //   0	493	0	this	BasketDAO
    //   0	493	1	id	String
    //   1	479	2	con	Connection
    //   3	462	3	pstmt	java.sql.PreparedStatement
    //   5	444	4	rs	java.sql.ResultSet
    //   8	218	5	pstmt2	java.sql.PreparedStatement
    //   11	273	6	rs2	java.sql.ResultSet
    //   15	189	7	sql	String
    //   24	467	8	vector	java.util.Vector
    //   33	285	9	basketList	java.util.List
    //   42	284	10	goodsList	java.util.List
    //   88	128	11	bb	BasketBean
    //   334	3	11	e	Exception
    //   251	47	12	gb	net.admin.goods.db.GoodsBean
    //   391	50	13	localObject	Object
    //   356	1	14	localSQLException	java.sql.SQLException
    //   371	1	14	localSQLException1	java.sql.SQLException
    //   386	1	14	localSQLException2	java.sql.SQLException
    //   408	1	14	localSQLException3	java.sql.SQLException
    //   423	1	14	localSQLException4	java.sql.SQLException
    //   438	1	14	localSQLException5	java.sql.SQLException
    //   458	1	14	localSQLException6	java.sql.SQLException
    //   473	1	14	localSQLException7	java.sql.SQLException
    //   488	1	14	localSQLException8	java.sql.SQLException
    // Exception table:
    //   from	to	target	type
    //   44	331	334	java/lang/Exception
    //   346	353	356	java/sql/SQLException
    //   362	368	371	java/sql/SQLException
    //   377	383	386	java/sql/SQLException
    //   44	341	391	finally
    //   398	405	408	java/sql/SQLException
    //   414	420	423	java/sql/SQLException
    //   429	435	438	java/sql/SQLException
    //   448	455	458	java/sql/SQLException
    //   464	470	473	java/sql/SQLException
    //   479	485	488	java/sql/SQLException
  }
  
  /* Error */
  public void basketDelete(int b_num)
  {
    // Byte code:
    //   0: aconst_null
    //   1: astore_2
    //   2: aconst_null
    //   3: astore_3
    //   4: aconst_null
    //   5: astore 4
    //   7: ldc 42
    //   9: astore 5
    //   11: aload_0
    //   12: invokespecial 44	net/basket/db/BasketDAO:getConnection	()Ljava/sql/Connection;
    //   15: astore_2
    //   16: ldc -23
    //   18: astore 5
    //   20: aload_2
    //   21: aload 5
    //   23: invokeinterface 47 2 0
    //   28: astore_3
    //   29: aload_3
    //   30: iconst_1
    //   31: iload_1
    //   32: invokeinterface 71 3 0
    //   37: aload_3
    //   38: invokeinterface 98 1 0
    //   43: pop
    //   44: goto +112 -> 156
    //   47: astore 6
    //   49: aload 6
    //   51: invokevirtual 101	java/lang/Exception:printStackTrace	()V
    //   54: aload 4
    //   56: ifnull +15 -> 71
    //   59: aload 4
    //   61: invokeinterface 104 1 0
    //   66: goto +5 -> 71
    //   69: astore 8
    //   71: aload_3
    //   72: ifnull +14 -> 86
    //   75: aload_3
    //   76: invokeinterface 107 1 0
    //   81: goto +5 -> 86
    //   84: astore 8
    //   86: aload_2
    //   87: ifnull +116 -> 203
    //   90: aload_2
    //   91: invokeinterface 108 1 0
    //   96: goto +107 -> 203
    //   99: astore 8
    //   101: goto +102 -> 203
    //   104: astore 7
    //   106: aload 4
    //   108: ifnull +15 -> 123
    //   111: aload 4
    //   113: invokeinterface 104 1 0
    //   118: goto +5 -> 123
    //   121: astore 8
    //   123: aload_3
    //   124: ifnull +14 -> 138
    //   127: aload_3
    //   128: invokeinterface 107 1 0
    //   133: goto +5 -> 138
    //   136: astore 8
    //   138: aload_2
    //   139: ifnull +14 -> 153
    //   142: aload_2
    //   143: invokeinterface 108 1 0
    //   148: goto +5 -> 153
    //   151: astore 8
    //   153: aload 7
    //   155: athrow
    //   156: aload 4
    //   158: ifnull +15 -> 173
    //   161: aload 4
    //   163: invokeinterface 104 1 0
    //   168: goto +5 -> 173
    //   171: astore 8
    //   173: aload_3
    //   174: ifnull +14 -> 188
    //   177: aload_3
    //   178: invokeinterface 107 1 0
    //   183: goto +5 -> 188
    //   186: astore 8
    //   188: aload_2
    //   189: ifnull +14 -> 203
    //   192: aload_2
    //   193: invokeinterface 108 1 0
    //   198: goto +5 -> 203
    //   201: astore 8
    //   203: return
    // Line number table:
    //   Java source line #183	-> byte code offset #0
    //   Java source line #184	-> byte code offset #2
    //   Java source line #185	-> byte code offset #4
    //   Java source line #186	-> byte code offset #7
    //   Java source line #189	-> byte code offset #11
    //   Java source line #191	-> byte code offset #16
    //   Java source line #192	-> byte code offset #20
    //   Java source line #193	-> byte code offset #29
    //   Java source line #195	-> byte code offset #37
    //   Java source line #196	-> byte code offset #44
    //   Java source line #197	-> byte code offset #49
    //   Java source line #199	-> byte code offset #54
    //   Java source line #200	-> byte code offset #71
    //   Java source line #201	-> byte code offset #86
    //   Java source line #198	-> byte code offset #104
    //   Java source line #199	-> byte code offset #106
    //   Java source line #200	-> byte code offset #123
    //   Java source line #201	-> byte code offset #138
    //   Java source line #202	-> byte code offset #153
    //   Java source line #199	-> byte code offset #156
    //   Java source line #200	-> byte code offset #173
    //   Java source line #201	-> byte code offset #188
    //   Java source line #203	-> byte code offset #203
    // Local variable table:
    //   start	length	slot	name	signature
    //   0	204	0	this	BasketDAO
    //   0	204	1	b_num	int
    //   1	192	2	con	Connection
    //   3	175	3	pstmt	java.sql.PreparedStatement
    //   5	157	4	rs	java.sql.ResultSet
    //   9	13	5	sql	String
    //   47	3	6	e	Exception
    //   104	50	7	localObject	Object
    //   69	1	8	localSQLException	java.sql.SQLException
    //   84	1	8	localSQLException1	java.sql.SQLException
    //   99	1	8	localSQLException2	java.sql.SQLException
    //   121	1	8	localSQLException3	java.sql.SQLException
    //   136	1	8	localSQLException4	java.sql.SQLException
    //   151	1	8	localSQLException5	java.sql.SQLException
    //   171	1	8	localSQLException6	java.sql.SQLException
    //   186	1	8	localSQLException7	java.sql.SQLException
    //   201	1	8	localSQLException8	java.sql.SQLException
    // Exception table:
    //   from	to	target	type
    //   11	44	47	java/lang/Exception
    //   59	66	69	java/sql/SQLException
    //   75	81	84	java/sql/SQLException
    //   90	96	99	java/sql/SQLException
    //   11	54	104	finally
    //   111	118	121	java/sql/SQLException
    //   127	133	136	java/sql/SQLException
    //   142	148	151	java/sql/SQLException
    //   161	168	171	java/sql/SQLException
    //   177	183	186	java/sql/SQLException
    //   192	198	201	java/sql/SQLException
  }
  
  /* Error */
  public void deleteBasket(String id)
  {
    // Byte code:
    //   0: aconst_null
    //   1: astore_2
    //   2: aconst_null
    //   3: astore_3
    //   4: aconst_null
    //   5: astore 4
    //   7: ldc 42
    //   9: astore 5
    //   11: aload_0
    //   12: invokespecial 44	net/basket/db/BasketDAO:getConnection	()Ljava/sql/Connection;
    //   15: astore_2
    //   16: ldc -20
    //   18: astore 5
    //   20: aload_2
    //   21: aload 5
    //   23: invokeinterface 47 2 0
    //   28: astore_3
    //   29: aload_3
    //   30: iconst_1
    //   31: aload_1
    //   32: invokeinterface 81 3 0
    //   37: aload_3
    //   38: invokeinterface 98 1 0
    //   43: pop
    //   44: goto +112 -> 156
    //   47: astore 6
    //   49: aload 6
    //   51: invokevirtual 101	java/lang/Exception:printStackTrace	()V
    //   54: aload 4
    //   56: ifnull +15 -> 71
    //   59: aload 4
    //   61: invokeinterface 104 1 0
    //   66: goto +5 -> 71
    //   69: astore 8
    //   71: aload_3
    //   72: ifnull +14 -> 86
    //   75: aload_3
    //   76: invokeinterface 107 1 0
    //   81: goto +5 -> 86
    //   84: astore 8
    //   86: aload_2
    //   87: ifnull +116 -> 203
    //   90: aload_2
    //   91: invokeinterface 108 1 0
    //   96: goto +107 -> 203
    //   99: astore 8
    //   101: goto +102 -> 203
    //   104: astore 7
    //   106: aload 4
    //   108: ifnull +15 -> 123
    //   111: aload 4
    //   113: invokeinterface 104 1 0
    //   118: goto +5 -> 123
    //   121: astore 8
    //   123: aload_3
    //   124: ifnull +14 -> 138
    //   127: aload_3
    //   128: invokeinterface 107 1 0
    //   133: goto +5 -> 138
    //   136: astore 8
    //   138: aload_2
    //   139: ifnull +14 -> 153
    //   142: aload_2
    //   143: invokeinterface 108 1 0
    //   148: goto +5 -> 153
    //   151: astore 8
    //   153: aload 7
    //   155: athrow
    //   156: aload 4
    //   158: ifnull +15 -> 173
    //   161: aload 4
    //   163: invokeinterface 104 1 0
    //   168: goto +5 -> 173
    //   171: astore 8
    //   173: aload_3
    //   174: ifnull +14 -> 188
    //   177: aload_3
    //   178: invokeinterface 107 1 0
    //   183: goto +5 -> 188
    //   186: astore 8
    //   188: aload_2
    //   189: ifnull +14 -> 203
    //   192: aload_2
    //   193: invokeinterface 108 1 0
    //   198: goto +5 -> 203
    //   201: astore 8
    //   203: return
    // Line number table:
    //   Java source line #207	-> byte code offset #0
    //   Java source line #208	-> byte code offset #2
    //   Java source line #209	-> byte code offset #4
    //   Java source line #210	-> byte code offset #7
    //   Java source line #213	-> byte code offset #11
    //   Java source line #215	-> byte code offset #16
    //   Java source line #216	-> byte code offset #20
    //   Java source line #217	-> byte code offset #29
    //   Java source line #219	-> byte code offset #37
    //   Java source line #220	-> byte code offset #44
    //   Java source line #221	-> byte code offset #49
    //   Java source line #223	-> byte code offset #54
    //   Java source line #224	-> byte code offset #71
    //   Java source line #225	-> byte code offset #86
    //   Java source line #222	-> byte code offset #104
    //   Java source line #223	-> byte code offset #106
    //   Java source line #224	-> byte code offset #123
    //   Java source line #225	-> byte code offset #138
    //   Java source line #226	-> byte code offset #153
    //   Java source line #223	-> byte code offset #156
    //   Java source line #224	-> byte code offset #173
    //   Java source line #225	-> byte code offset #188
    //   Java source line #227	-> byte code offset #203
    // Local variable table:
    //   start	length	slot	name	signature
    //   0	204	0	this	BasketDAO
    //   0	204	1	id	String
    //   1	192	2	con	Connection
    //   3	175	3	pstmt	java.sql.PreparedStatement
    //   5	157	4	rs	java.sql.ResultSet
    //   9	13	5	sql	String
    //   47	3	6	e	Exception
    //   104	50	7	localObject	Object
    //   69	1	8	localSQLException	java.sql.SQLException
    //   84	1	8	localSQLException1	java.sql.SQLException
    //   99	1	8	localSQLException2	java.sql.SQLException
    //   121	1	8	localSQLException3	java.sql.SQLException
    //   136	1	8	localSQLException4	java.sql.SQLException
    //   151	1	8	localSQLException5	java.sql.SQLException
    //   171	1	8	localSQLException6	java.sql.SQLException
    //   186	1	8	localSQLException7	java.sql.SQLException
    //   201	1	8	localSQLException8	java.sql.SQLException
    // Exception table:
    //   from	to	target	type
    //   11	44	47	java/lang/Exception
    //   59	66	69	java/sql/SQLException
    //   75	81	84	java/sql/SQLException
    //   90	96	99	java/sql/SQLException
    //   11	54	104	finally
    //   111	118	121	java/sql/SQLException
    //   127	133	136	java/sql/SQLException
    //   142	148	151	java/sql/SQLException
    //   161	168	171	java/sql/SQLException
    //   177	183	186	java/sql/SQLException
    //   192	198	201	java/sql/SQLException
  }
}
